fauna/__init__.py
fauna/client/__init__.py
fauna/client/client.py
fauna/client/endpoints.py
fauna/client/headers.py
fauna/client/retryable.py
fauna/client/utils.py
fauna/encoding/__init__.py
fauna/encoding/decoder.py
fauna/encoding/encoder.py
fauna/encoding/wire_protocol.py
fauna/errors/__init__.py
fauna/errors/errors.py
fauna/http/__init__.py
fauna/http/http_client.py
fauna/http/httpx_client.py
fauna/query/__init__.py
fauna/query/models.py
fauna/query/query_builder.py
fauna/query/template.py
fauna-2.4.0.dist-info/LICENSE
fauna-2.4.0.dist-info/METADATA
fauna-2.4.0.dist-info/WHEEL
fauna-2.4.0.dist-info/top_level.txt
fauna-2.4.0.dist-info/RECORD
