Metadata-Version: 2.1
Name: fauna
Version: 2.4.0
Summary: Fauna Python driver for FQL 10+
Home-page: https://github.com/fauna/fauna-python
Author: Fauna, Inc
Author-email: priority@fauna.com
License: MPL 2.0
Keywords: faunadb fauna
Platform: UNKNOWN
Classifier: Development Status :: 5 - Production/Stable
Classifier: Intended Audience :: Developers
Classifier: License :: OSI Approved :: Mozilla Public License 2.0 (MPL 2.0)
Classifier: Programming Language :: Python :: 3
Classifier: Programming Language :: Python :: 3.9
Classifier: Programming Language :: Python :: 3.10
Classifier: Programming Language :: Python :: 3.11
Classifier: Programming Language :: Python :: 3.12
Classifier: Topic :: Database
Classifier: Topic :: Database :: Front-Ends
Classifier: Operating System :: MacOS :: MacOS X
Classifier: Operating System :: Microsoft :: Windows
Classifier: Operating System :: Unix
Requires-Python: >=3.9, <4
License-File: LICENSE
Requires-Dist: iso8601 (==2.1.0)
Requires-Dist: future (==1.0.0)
Requires-Dist: httpx[http2] (==0.28.*)
Provides-Extra: lint
Requires-Dist: yapf (==0.40.1) ; extra == 'lint'
Provides-Extra: test
Requires-Dist: pytest (==8.1.1) ; extra == 'test'
Requires-Dist: pytest-env (==1.1.3) ; extra == 'test'
Requires-Dist: pytest-cov (==5.0.0) ; extra == 'test'
Requires-Dist: pytest-httpx (==0.35.0) ; extra == 'test'
Requires-Dist: pytest-subtests (==0.12.1) ; extra == 'test'
